LICENSE
MANIFEST.in
README.md
setup.cfg
setup.py
_tests/__init__.py
_tests/test_pput.py
_tests/test_snap.py
_tests/test_ssh_sync.py
z3/__init__.py
z3/compressors.py
z3/config.py
z3/get.py
z3/pput.py
z3/s3_mp_cleanup.py
z3/snap.py
z3/ssh_sync.py
z3/z3.conf
z3.egg-info/PKG-INFO
z3.egg-info/SOURCES.txt
z3.egg-info/dependency_links.txt
z3.egg-info/entry_points.txt
z3.egg-info/requires.txt
z3.egg-info/top_level.txt