Metadata-Version: 1.1
Name: z3
Version: 0.1.8
Summary: Backup ZFS snapshots to S3
Home-page: https://github.com/presslabs/z3
Author: PressLabs SRL
Author-email: contact@presslabs.com
License: UNKNOWN
Keywords: ZFS backup
Platform: any
Classifier: Development Status :: 4 - Beta
Classifier: Environment :: Console
Classifier: License :: OSI Approved :: Apache Software License
Classifier: Topic :: System :: Archiving :: Backup
Classifier: Topic :: Utilities
